{
    "ADaCGH2": [
        "snapCGH"
    ],
    "ADImpute": [],
    "affycoretools": [
        "ReportingTools",
        "biovizBase",
        "ensembldb",
        "ggbio",
        "oligoClasses"
    ],
    "aggregateBioVar": [],
    "AgiMicroRna": [
        "ReportingTools",
        "affycoretools",
        "biovizBase",
        "ensembldb",
        "ggbio",
        "oligoClasses"
    ],
    "AHMassBank": [],
    "airpart": [
        "scater"
    ],
    "alabaster": [
        "alabaster.mae",
        "alabaster.spatial",
        "alabaster.vcf"
    ],
    "alabaster.mae": [],
    "alabaster.spatial": [],
    "alabaster.vcf": [],
    "AllelicImbalance": [
        "Gviz",
        "biovizBase",
        "ensembldb"
    ],
    "ANCOMBC": [
        "mia",
        "scater"
    ],
    "annotatr": [
        "regioneR"
    ],
    "APAlyzer": [],
    "appreci8R": [],
    "ArrayExpress": [
        "oligo",
        "oligoClasses"
    ],
    "arrayMvout": [
        "lumi",
        "methylumi",
        "minfi"
    ],
    "ASpli": [
        "Gviz",
        "biovizBase",
        "ensembldb"
    ],
    "ATACCoGAPS": [
        "motifmatchr"
    ],
    "ATACseqQC": [
        "ChIPpeakAnno",
        "ensembldb",
        "motifStack",
        "regioneR"
    ],
    "ATACseqTFEA": [
        "motifmatchr"
    ],
    "atSNP": [
        "motifStack"
    ],
    "BadRegionFinder": [],
    "BANDITS": [
        "DRIMSeq"
    ],
    "bandle": [
        "pRoloc"
    ],
    "banocc": [],
    "BASiCS": [],
    "BASiCStan": [
        "BASiCS"
    ],
    "BayesSpace": [
        "scater"
    ],
    "BBCAnalyzer": [],
    "BEclear": [],
    "benchdamic": [
        "ANCOMBC",
        "mia",
        "scater"
    ],
    "BGmix": [],
    "bgx": [],
    "bigmelon": [
        "lumi",
        "methylumi",
        "minfi",
        "wateRmelon"
    ],
    "BindingSiteFinder": [
        "Gviz",
        "biovizBase",
        "ensembldb"
    ],
    "bioCancer": [],
    "biovizBase": [
        "ensembldb"
    ],
    "biscuiteer": [
        "annotatr",
        "dmrseq",
        "regioneR"
    ],
    "BOBaFIT": [
        "biovizBase",
        "ensembldb",
        "ggbio"
    ],
    "borealis": [],
    "brainflowprobes": [
        "GenomicFiles",
        "biovizBase",
        "derfinder",
        "derfinderPlot",
        "ensembldb",
        "ggbio"
    ],
    "BubbleTree": [
        "biovizBase",
        "ensembldb"
    ],
    "BufferedMatrix": [],
    "BufferedMatrixMethods": [
        "BufferedMatrix"
    ],
    "BUSpaRse": [
        "ensembldb"
    ],
    "CAFE": [
        "biovizBase",
        "ensembldb",
        "ggbio"
    ],
    "CAGEfightR": [
        "GenomicFiles",
        "GenomicInteractions",
        "Gviz",
        "biovizBase",
        "ensembldb"
    ],
    "cageminer": [
        "biovizBase",
        "ensembldb",
        "ggbio"
    ],
    "CAGEr": [
        "CAGEfightR",
        "GenomicFiles",
        "GenomicInteractions",
        "Gviz",
        "biovizBase",
        "ensembldb"
    ],
    "canceR": [],
    "cardelino": [],
    "CATALYST": [
        "FlowSOM",
        "scater"
    ],
    "cbaf": [
        "RTCGAToolbox",
        "cBioPortalData"
    ],
    "cBioPortalData": [
        "RTCGAToolbox"
    ],
    "CBNplot": [],
    "celda": [
        "scater"
    ],
    "CelliD": [
        "scater"
    ],
    "CellMixS": [
        "scater"
    ],
    "censcyt": [
        "FlowSOM",
        "diffcyt"
    ],
    "ChAMP": [
        "DMRcate",
        "Gviz",
        "biovizBase",
        "ensembldb",
        "lumi",
        "methylumi",
        "minfi",
        "missMethyl",
        "wateRmelon"
    ],
    "ChIC": [],
    "chihaya": [],
    "chimeraviz": [
        "Gviz",
        "biovizBase",
        "ensembldb"
    ],
    "ChIPexoQual": [
        "biovizBase",
        "ensembldb"
    ],
    "ChIPpeakAnno": [
        "ensembldb",
        "regioneR"
    ],
    "ChIPQC": [],
    "ChIPXpress": [
        "frma",
        "oligo",
        "oligoClasses"
    ],
    "ChromSCape": [
        "scater"
    ],
    "cicero": [
        "Gviz",
        "biovizBase",
        "ensembldb"
    ],
    "circRNAprofiler": [
        "gwascat"
    ],
    "CircSeqAlignTk": [
        "Rhisat2"
    ],
    "CiteFuse": [],
    "clipper": [],
    "cn.farms": [
        "oligo",
        "oligoClasses"
    ],
    "CNVfilteR": [
        "CopyNumberPlots",
        "biovizBase",
        "ensembldb",
        "karyoploteR",
        "regioneR"
    ],
    "CNViz": [
        "CopyNumberPlots",
        "biovizBase",
        "ensembldb",
        "karyoploteR",
        "regioneR"
    ],
    "CNVrd2": [],
    "COCOA": [],
    "comapr": [
        "Gviz",
        "biovizBase",
        "ensembldb"
    ],
    "coMET": [
        "Gviz",
        "biovizBase",
        "ensembldb"
    ],
    "coMethDMR": [],
    "compEpiTools": [
        "Gviz",
        "biovizBase",
        "ensembldb",
        "methylPipe"
    ],
    "condiments": [
        "distinct",
        "scater"
    ],
    "CONFESS": [],
    "consensusDE": [
        "RUVSeq",
        "ensembldb"
    ],
    "contiBAIT": [
        "GenomicFiles"
    ],
    "conumee": [
        "minfi"
    ],
    "CopyNumberPlots": [
        "biovizBase",
        "ensembldb",
        "karyoploteR",
        "regioneR"
    ],
    "COTAN": [],
    "crisprDesign": [],
    "crisprseekplus": [
        "ChIPpeakAnno",
        "GUIDEseq",
        "ensembldb",
        "regioneR"
    ],
    "crisprVerse": [
        "Gviz",
        "biovizBase",
        "crisprDesign",
        "crisprViz",
        "ensembldb"
    ],
    "crisprViz": [
        "Gviz",
        "biovizBase",
        "crisprDesign",
        "ensembldb"
    ],
    "crlmm": [
        "oligoClasses"
    ],
    "crossmeta": [
        "oligo",
        "oligoClasses"
    ],
    "CTSV": [],
    "cummeRbund": [
        "Gviz",
        "biovizBase",
        "ensembldb"
    ],
    "customProDB": [],
    "CyTOFpower": [
        "FlowSOM",
        "diffcyt"
    ],
    "cytofQC": [
        "CATALYST",
        "FlowSOM",
        "scater"
    ],
    "cytomapper": [],
    "cytoviewer": [
        "cytomapper"
    ],
    "dagLogo": [
        "motifStack"
    ],
    "DAMEfinder": [],
    "DaMiRseq": [],
    "decompTumor2Sig": [],
    "deconvR": [
        "minfi"
    ],
    "deepSNV": [],
    "DeMixT": [],
    "derfinder": [
        "GenomicFiles"
    ],
    "derfinderPlot": [
        "GenomicFiles",
        "biovizBase",
        "derfinder",
        "ensembldb",
        "ggbio"
    ],
    "DEScan2": [
        "ChIPpeakAnno",
        "ensembldb",
        "regioneR"
    ],
    "DESpace": [],
    "diffcyt": [
        "FlowSOM"
    ],
    "DifferentialRegulation": [
        "BANDITS",
        "DRIMSeq"
    ],
    "diffUTR": [
        "ensembldb"
    ],
    "Dino": [],
    "distinct": [
        "scater"
    ],
    "DMRcate": [
        "Gviz",
        "biovizBase",
        "ensembldb",
        "methylumi",
        "minfi",
        "missMethyl"
    ],
    "DMRforPairs": [
        "Gviz",
        "biovizBase",
        "ensembldb"
    ],
    "dmrseq": [
        "annotatr",
        "regioneR"
    ],
    "DominoEffect": [],
    "DRIMSeq": [],
    "drugTargetInteractions": [
        "ensembldb"
    ],
    "DrugVsDisease": [
        "ArrayExpress",
        "oligo",
        "oligoClasses"
    ],
    "ELMER": [
        "Gviz",
        "biovizBase",
        "ensembldb"
    ],
    "enhancerHomologSearch": [
        "motifmatchr"
    ],
    "ENmix": [
        "minfi"
    ],
    "enrichTF": [
        "motifmatchr"
    ],
    "ensembldb": [],
    "ensemblVEP": [],
    "epialleleR": [],
    "epigraHMM": [],
    "epimutacions": [
        "Gviz",
        "biovizBase",
        "ensembldb",
        "minfi"
    ],
    "epivizr": [
        "ensembldb",
        "epivizrData"
    ],
    "epivizrChart": [
        "ensembldb",
        "epivizrData"
    ],
    "epivizrData": [
        "ensembldb"
    ],
    "epivizrStandalone": [
        "ensembldb",
        "epivizr",
        "epivizrData"
    ],
    "erma": [
        "GenomicFiles"
    ],
    "esATAC": [
        "motifmatchr"
    ],
    "escheR": [
        "scater"
    ],
    "EventPointer": [],
    "ExperimentHubData": [],
    "ExperimentSubset": [],
    "extraChIPs": [
        "GenomicInteractions",
        "Gviz",
        "biovizBase",
        "ensembldb"
    ],
    "famat": [],
    "fcScan": [],
    "FEAST": [],
    "ffpe": [
        "lumi",
        "methylumi",
        "minfi"
    ],
    "flagme": [],
    "FLAMES": [
        "biovizBase",
        "ensembldb",
        "ggbio",
        "scater"
    ],
    "FlowSOM": [],
    "frma": [
        "oligo",
        "oligoClasses"
    ],
    "funtooNorm": [
        "minfi"
    ],
    "GA4GHclient": [],
    "GA4GHshiny": [
        "GA4GHclient"
    ],
    "GARS": [
        "DaMiRseq"
    ],
    "GDCRNATools": [],
    "genbankr": [],
    "GeneStructureTools": [
        "Gviz",
        "biovizBase",
        "ensembldb"
    ],
    "GenomicFiles": [],
    "GenomicInteractions": [
        "Gviz",
        "biovizBase",
        "ensembldb"
    ],
    "GenomicOZone": [
        "biovizBase",
        "ensembldb",
        "ggbio"
    ],
    "GenVisR": [],
    "GeoDiff": [
        "GeomxTools",
        "NanoStringNCTools"
    ],
    "GeomxTools": [
        "NanoStringNCTools"
    ],
    "GeoTcgaData": [],
    "gespeR": [],
    "ggbio": [
        "biovizBase",
        "ensembldb"
    ],
    "ggspavis": [],
    "gmapR": [],
    "GmicR": [],
    "GRENITS": [],
    "GUIDEseq": [
        "ChIPpeakAnno",
        "ensembldb",
        "regioneR"
    ],
    "Gviz": [
        "biovizBase",
        "ensembldb"
    ],
    "gwascat": [],
    "gwasurvivr": [],
    "HelloRanges": [],
    "HiCDCPlus": [
        "GenomicInteractions",
        "Gviz",
        "biovizBase",
        "ensembldb"
    ],
    "hierGWAS": [],
    "HTSeqGenie": [
        "VariantTools",
        "gmapR"
    ],
    "icetea": [],
    "iCheck": [
        "lumi",
        "methylumi",
        "minfi"
    ],
    "ideal": [
        "pcaExplorer"
    ],
    "IgGeneUsage": [],
    "igvR": [],
    "IMAS": [],
    "imcRtools": [
        "cytomapper"
    ],
    "infinityFlow": [],
    "intansv": [
        "biovizBase",
        "ensembldb",
        "ggbio"
    ],
    "IntEREst": [
        "GenomicFiles"
    ],
    "IRISFGM": [
        "scater"
    ],
    "IsoformSwitchAnalyzeR": [
        "DRIMSeq",
        "ensembldb",
        "tximeta"
    ],
    "ITALICS": [
        "oligo",
        "oligoClasses"
    ],
    "karyoploteR": [
        "biovizBase",
        "ensembldb",
        "regioneR"
    ],
    "katdetectr": [],
    "kissDE": [],
    "KnowSeq": [],
    "lineagespot": [],
    "lisaClust": [
        "spicyR"
    ],
    "lumi": [
        "methylumi",
        "minfi"
    ],
    "M3Drop": [],
    "MADSEQ": [],
    "MAGAR": [
        "RnBeads",
        "crlmm",
        "methylumi",
        "minfi",
        "oligoClasses"
    ],
    "magpie": [],
    "MAIT": [],
    "mariner": [],
    "maser": [
        "Gviz",
        "biovizBase",
        "ensembldb"
    ],
    "MatrixRider": [],
    "MBECS": [],
    "mBPCR": [
        "oligoClasses"
    ],
    "mCSEA": [
        "Gviz",
        "biovizBase",
        "ensembldb"
    ],
    "MEAL": [
        "Gviz",
        "biovizBase",
        "ensembldb",
        "methylumi",
        "minfi",
        "missMethyl"
    ],
    "MEAT": [
        "lumi",
        "methylumi",
        "minfi",
        "wateRmelon"
    ],
    "MEB": [
        "scater"
    ],
    "MetaboSignal": [
        "ensembldb"
    ],
    "MetaCyto": [
        "FlowSOM"
    ],
    "metagene": [
        "ensembldb"
    ],
    "metaMS": [],
    "MetaPhOR": [],
    "MethylAid": [
        "minfi"
    ],
    "methylCC": [
        "minfi"
    ],
    "methylclock": [
        "ExperimentHubData",
        "minfi"
    ],
    "methylGSA": [
        "methylumi",
        "minfi",
        "missMethyl"
    ],
    "methylPipe": [
        "Gviz",
        "biovizBase",
        "ensembldb"
    ],
    "methylSig": [],
    "methylumi": [
        "minfi"
    ],
    "mia": [
        "scater"
    ],
    "miaViz": [
        "mia",
        "scater"
    ],
    "microbiomeMarker": [
        "ANCOMBC",
        "mia",
        "scater"
    ],
    "mimager": [
        "oligo",
        "oligoClasses"
    ],
    "MineICA": [
        "lumi",
        "methylumi",
        "minfi"
    ],
    "minfi": [],
    "MinimumDistance": [
        "VanillaICE",
        "crlmm",
        "oligoClasses"
    ],
    "miRLAB": [],
    "miRSM": [
        "miRspongeR"
    ],
    "miRspongeR": [],
    "missMethyl": [
        "methylumi",
        "minfi"
    ],
    "mitoClone2": [
        "deepSNV"
    ],
    "MMAPPR2": [
        "VariantTools",
        "ensemblVEP",
        "gmapR"
    ],
    "MoleculeExperiment": [],
    "monaLisa": [],
    "MoonlightR": [],
    "mosbi": [
        "QUBIC"
    ],
    "motifbreakR": [
        "Gviz",
        "biovizBase",
        "ensembldb",
        "motifStack"
    ],
    "motifmatchr": [],
    "motifStack": [],
    "msgbsR": [
        "biovizBase",
        "ensembldb",
        "ggbio"
    ],
    "msImpute": [],
    "MSPrep": [],
    "multicrispr": [
        "biovizBase",
        "ensembldb",
        "karyoploteR",
        "regioneR"
    ],
    "multiSight": [],
    "mumosa": [],
    "MungeSumstats": [],
    "muscat": [
        "scater"
    ],
    "musicatk": [
        "decompTumor2Sig"
    ],
    "MutationalPatterns": [],
    "myvariant": [],
    "NADfinder": [
        "ATACseqQC",
        "ChIPpeakAnno",
        "Gviz",
        "biovizBase",
        "ensembldb",
        "motifStack",
        "regioneR",
        "trackViewer"
    ],
    "NanoMethViz": [],
    "NanoStringNCTools": [],
    "ndexr": [],
    "netSmooth": [
        "scater"
    ],
    "netZooR": [
        "minfi",
        "quantro",
        "yarn"
    ],
    "nnSVG": [],
    "octad": [
        "RUVSeq"
    ],
    "ODER": [
        "GenomicFiles",
        "derfinder"
    ],
    "OGRE": [
        "Gviz",
        "biovizBase",
        "ensembldb"
    ],
    "oligo": [
        "oligoClasses"
    ],
    "oligoClasses": [],
    "omada": [],
    "omicRexposome": [],
    "OmicsLonDA": [],
    "OMICsPCA": [
        "HelloRanges"
    ],
    "OutSplice": [
        "Repitools"
    ],
    "PAA": [],
    "pageRank": [
        "motifmatchr"
    ],
    "pairedGSEA": [],
    "PanomiR": [],
    "pcaExplorer": [],
    "pdInfoBuilder": [
        "oligo",
        "oligoClasses"
    ],
    "peco": [
        "scater"
    ],
    "PFP": [],
    "PhenStat": [],
    "Pigengene": [],
    "PING": [
        "Gviz",
        "biovizBase",
        "ensembldb"
    ],
    "pipeComp": [
        "scater"
    ],
    "PloGO2": [],
    "ppcseq": [],
    "preciseTAD": [],
    "primirTSS": [
        "Gviz",
        "biovizBase",
        "ensembldb"
    ],
    "profileplyr": [],
    "pRoloc": [],
    "pRolocGUI": [
        "pRoloc"
    ],
    "PROPS": [],
    "proteasy": [
        "ensembldb"
    ],
    "ProteoDisco": [],
    "psichomics": [
        "GenomicFiles",
        "derfinder",
        "recount"
    ],
    "puma": [
        "oligo",
        "oligoClasses"
    ],
    "PureCN": [],
    "Pviz": [
        "Gviz",
        "biovizBase",
        "ensembldb"
    ],
    "qsmooth": [],
    "qsvaR": [],
    "quantro": [
        "minfi"
    ],
    "QuasR": [
        "GenomicFiles"
    ],
    "QUBIC": [],
    "R3CPET": [
        "biovizBase",
        "ensembldb",
        "ggbio"
    ],
    "R453Plus1Toolbox": [],
    "RareVariantVis": [],
    "Rbec": [],
    "RCASPAR": [],
    "RcisTarget": [],
    "RcwlPipelines": [],
    "rebook": [],
    "recount": [
        "GenomicFiles",
        "derfinder"
    ],
    "recountmethylation": [
        "minfi"
    ],
    "REDseq": [
        "ChIPpeakAnno",
        "ensembldb",
        "regioneR"
    ],
    "regioneR": [],
    "regioneReloaded": [
        "regioneR"
    ],
    "regionReport": [
        "GenomicFiles",
        "derfinder"
    ],
    "regutools": [
        "Gviz",
        "biovizBase",
        "ensembldb"
    ],
    "REMP": [
        "minfi"
    ],
    "Repitools": [],
    "ReportingTools": [
        "biovizBase",
        "ensembldb",
        "ggbio"
    ],
    "RESOLVE": [
        "MutationalPatterns"
    ],
    "retrofit": [],
    "ReUseData": [
        "RcwlPipelines"
    ],
    "RgnTX": [
        "regioneR"
    ],
    "rgsepd": [],
    "Rhisat2": [],
    "RiboCrypt": [],
    "RiboDiPA": [],
    "RiboProfiling": [
        "biovizBase",
        "ensembldb",
        "ggbio"
    ],
    "ribosomeProfilingQC": [
        "RUVSeq",
        "motifStack"
    ],
    "RIPAT": [
        "biovizBase",
        "ensembldb",
        "karyoploteR",
        "regioneR"
    ],
    "RITAN": [
        "ensembldb"
    ],
    "RLSeq": [
        "regioneR"
    ],
    "RNAAgeCalc": [
        "GenomicFiles",
        "derfinder",
        "recount"
    ],
    "rnaEditr": [],
    "RNAinteract": [],
    "RNAmodR": [
        "Gviz",
        "biovizBase",
        "ensembldb"
    ],
    "RNAmodR.AlkAnilineSeq": [
        "Gviz",
        "RNAmodR",
        "biovizBase",
        "ensembldb"
    ],
    "RNAmodR.ML": [
        "Gviz",
        "RNAmodR",
        "biovizBase",
        "ensembldb"
    ],
    "RNAmodR.RiboMethSeq": [
        "Gviz",
        "RNAmodR",
        "biovizBase",
        "ensembldb"
    ],
    "RnaSeqSampleSize": [
        "GenomicFiles",
        "derfinder",
        "recount"
    ],
    "RnBeads": [
        "methylumi",
        "minfi"
    ],
    "Rqc": [
        "GenomicFiles",
        "biovizBase",
        "ensembldb"
    ],
    "RTCGAToolbox": [],
    "RUVSeq": [],
    "SCAN.UPC": [
        "oligo",
        "oligoClasses"
    ],
    "scanMiRApp": [
        "ensembldb"
    ],
    "scater": [],
    "scBFA": [],
    "sccomp": [],
    "scDblFinder": [
        "scater"
    ],
    "scDD": [],
    "scFeatures": [
        "SingleCellSignalR",
        "ensembldb"
    ],
    "schex": [],
    "scMerge": [
        "M3Drop",
        "scater"
    ],
    "scMET": [],
    "scmeth": [
        "annotatr",
        "regioneR"
    ],
    "scone": [
        "RUVSeq"
    ],
    "scoreInvHap": [],
    "scRNAseqApp": [],
    "scruff": [
        "biovizBase",
        "ensembldb",
        "ggbio"
    ],
    "scTensor": [
        "schex"
    ],
    "scTGIF": [
        "schex"
    ],
    "scTreeViz": [
        "ensembldb",
        "epivizr",
        "epivizrData",
        "scater"
    ],
    "scviR": [
        "scater"
    ],
    "segmenter": [],
    "selectKSigs": [],
    "seqArchRplus": [],
    "seqCAT": [],
    "SEtools": [],
    "SGCP": [],
    "shinyepico": [
        "minfi"
    ],
    "shinyMethyl": [
        "minfi"
    ],
    "SigCheck": [],
    "signatureSearch": [],
    "signeR": [],
    "signifinder": [
        "ensembldb"
    ],
    "SigsPack": [],
    "SimBindProfiles": [],
    "simpleSeg": [
        "cytomapper"
    ],
    "SingleCellSignalR": [],
    "singleCellTK": [
        "M3Drop",
        "celda",
        "ensembldb",
        "scDblFinder",
        "scMerge",
        "scater"
    ],
    "SingleMoleculeFootprinting": [
        "GenomicFiles",
        "QuasR"
    ],
    "skewr": [
        "lumi",
        "methylumi",
        "minfi",
        "wateRmelon"
    ],
    "SMITE": [],
    "snapCGH": [],
    "SNPhood": [],
    "SomaticSignatures": [
        "biovizBase",
        "ensembldb",
        "ggbio"
    ],
    "Spaniel": [
        "scater"
    ],
    "spaSim": [],
    "spatialDE": [],
    "SpatialDecon": [
        "GeomxTools",
        "NanoStringNCTools"
    ],
    "SpatialFeatureExperiment": [],
    "spatialHeatmap": [
        "scater"
    ],
    "SpatialOmicsOverlay": [
        "GeomxTools",
        "NanoStringNCTools"
    ],
    "spatzie": [
        "GenomicInteractions",
        "Gviz",
        "biovizBase",
        "ensembldb",
        "motifmatchr"
    ],
    "SPIAT": [],
    "spicyR": [],
    "SPLINTER": [
        "Gviz",
        "biovizBase",
        "ensembldb"
    ],
    "SpotClean": [],
    "standR": [
        "RUVSeq"
    ],
    "staRank": [],
    "stJoincount": [],
    "StructuralVariantAnnotation": [],
    "svaNUMT": [
        "StructuralVariantAnnotation"
    ],
    "svaRetro": [
        "StructuralVariantAnnotation"
    ],
    "TBSignatureProfiler": [],
    "terraTCGAdata": [],
    "TFHAZ": [],
    "TileDBArray": [],
    "TimiRGeN": [],
    "TitanCNA": [],
    "tLOH": [],
    "trackViewer": [
        "Gviz",
        "biovizBase",
        "ensembldb"
    ],
    "tradeSeq": [],
    "traviz": [],
    "treekoR": [
        "FlowSOM",
        "diffcyt"
    ],
    "tricycle": [
        "scater"
    ],
    "trigger": [],
    "tscR": [],
    "TVTB": [
        "Gviz",
        "biovizBase",
        "ensemblVEP",
        "ensembldb"
    ],
    "tximeta": [
        "ensembldb"
    ],
    "Ularcirc": [],
    "UMI4Cats": [
        "regioneR"
    ],
    "uncoverappLib": [
        "Gviz",
        "biovizBase",
        "ensembldb"
    ],
    "Uniquorn": [],
    "VAExprs": [
        "scater"
    ],
    "VanillaICE": [
        "crlmm",
        "oligoClasses"
    ],
    "VariantFiltering": [
        "Gviz",
        "biovizBase",
        "ensembldb"
    ],
    "VariantTools": [],
    "VaSP": [],
    "VCFArray": [
        "GenomicFiles"
    ],
    "VDJdive": [],
    "velociraptor": [],
    "vissE": [],
    "Voyager": [
        "SpatialFeatureExperiment"
    ],
    "vtpnet": [
        "gwascat"
    ],
    "vulcan": [
        "ChIPpeakAnno",
        "ensembldb",
        "regioneR"
    ],
    "wateRmelon": [
        "lumi",
        "methylumi",
        "minfi"
    ],
    "YAPSA": [
        "SomaticSignatures",
        "biovizBase",
        "ensembldb",
        "ggbio"
    ],
    "yarn": [
        "minfi",
        "quantro"
    ],
    "ZygosityPredictor": []
}